{
  "name": "Manuel Ingram",
  "age": 58,
  "address": {
    "street": "Vufak Extension",
    "city": "Dughoti",
    "state": "PA",
    "zip": "78698"
  },
  "contact": {
    "phone": "(688) 359-3813",
    "servicePhone": "800114778"
  },
  "birthday": "1976-05-08T00:38:03.175Z",
  "ip": "97.84.84.190",
  "foo": "bar",
  "profile": {
    "about": "Wi rasbiv misazad moj ni lu uhrotej onaovococ wucimiz udugpor kiwel goceb. Kibub ohu upevacu owuho vabcimom eka jelfuc ruvbug coc tolu lacul vekuj er. Ec bajpinpoj zu ram go wuske emoguhik lor ri famlo nilib saumu vi mobakji.",
    "bio": "Zigkuwi wuramug givaca sotwu noetabu ne hupotted nok ejo dek peshe lorom rat witu. Wo lahoso gu aji ikizuhu nazca la gad okufiddoz fafueti culsa apuricma nicwivbar ce opdal gehcaze. Ida apfuno to ubvovjig diem ha fiita dav watapif ni pimdusma mamwu. Zetoluw jajeh pehmako hap tipmikpa dienifo etwopzeh nate wiev ajcaac zocifvur kewisato ju za zen bu kec tewomeute. Egohu totju ilufat ja ase jokur dimjibpuj recpel ma molvez vupvak gaek."
  },
  "apiKey": "22b352b4c4bbde848a514c4383d5ed5bdae77f30ddfbe3106c91e03a02e6feed",
  "currency": {
    "code": "JEP",
    "name": "Jersey Pound"
  }
}