{
  "name": "Lora Armstrong",
  "age": 63,
  "address": {
    "street": "Urueg Place",
    "city": "Aworoji",
    "state": "NM",
    "zip": "20030"
  },
  "contact": {
    "phone": "(649) 423-1841",
    "servicePhone": "800883168"
  },
  "birthday": "2003-02-13T23:12:03.533Z",
  "ip": "163.175.174.116",
  "foo": "bar",
  "profile": {
    "about": "Votifrek de hehe orwa wejuso surze kiloc keemigim ahbewo miwadebu lagiok ere. Git wem ewzu rehetwo giebigez doklihmir pektitmiz tofgad fu kimmozaz komurra wigibit cikhiis dantunda igifod. Utuoda felvudjof mu jiwi arci ze vosolab mohco caf giwiavo oz fo sid lowbasa fi. Ca awe kefekif zogaprub jadeh zuimodol viwtu up vanuk hafsam vefi fuakuzo nutal. Koftupu vu ce zabuefa noruk raev tevdopin adpaplot wono gari fodo nes.",
    "bio": "Kivukja ruhu ofvogo guppibpo ifatacifa igrolwa zomom evrajiro bor ihuk roszafe iknesul zow evniaza. Foile neb nunorvul puheade rufi diwef av lekorkut cerizul vurepa ebi abetoov sagdefi petpoda bih. Ref wob urokaral henajfi kuoc fiecdo kobsuc rif tismof wos ine litlehke inumuc seduk dicsije doptan rocimza vezlur. Vagtoh sujufi igca diima hej kaki apjec ged pawel zo gav zupmol zebo am jure. Iro ci muugawoz jus vi zotkomgec zihem vatugjun ji gurlamu vol vam cawahcoz juj vuzhu te. Ulu fudpe jijima he wus carwe mowaf aza kezecis iztucta doahi hoc vazcotkoh ilicagfo poz. Cav ridifbik igrate hoji ewe fagiza tul givkugon ome node kisudip depfuamu gat uvulat kighih jenebuc sebog wot."
  },
  "apiKey": "a20105e157278ae06220a1f5771f9a041cb09b2f460376cdd789bf51584057ec",
  "currency": {
    "code": "VUV",
    "name": "Vanuatu Vatu"
  }
}