{
  "name": "Joshua Fields",
  "age": 48,
  "address": {
    "street": "Deim Heights",
    "city": "Riwpefmo",
    "state": "NE",
    "zip": "15309"
  },
  "contact": {
    "phone": "(985) 855-5165",
    "servicePhone": "800723371"
  },
  "birthday": "1960-12-23T13:35:27.726Z",
  "ip": "139.88.230.107",
  "foo": "bar",
  "profile": {
    "about": "Idu hagicem ba bah lumkiw ce gudtoj ilagaw wahtew osuoz ozpuj bojdobgo de ub ge pasfuzaj wud. Huhfocek si jeceg gobogfi fe rouja low uro sotucid wiwlamip segris mutug hoobtal eru. Lo fetuur dumizta huogo bemtoide sivto benkinbo mupojmo butet uji afita jec fifsohcep teppuv lekzu bosgivhec cofwe ikivorfa.",
    "bio": "Afluuji nejne we jegimocan ehadu hupiaf totwiw du mejjeta ajotat tocephuk ejpiul mikvorim. Viwzowpup hu za oda ta hap suwuneub oguzaeb hidecagag di cuwel sosambig ve lijal izosati boztek mipehiw zunmob. Awe wul lepew dilve sowfuag ruk pir eki meteda buucivi cep to. Abwaodo vozpo wagselvum kasnok faf ki subdiodo fota wevati idvol gozgoj bit laupa vuakueze kiuka ed."
  },
  "apiKey": "d9a9b9597474b24ef116ec4d796803ad4ea5a6e48a1098431877ebd18a1108a2",
  "currency": {
    "code": "DJF",
    "name": "Djibouti Franc"
  }
}