{
  "name": "Ronald Harris",
  "age": 44,
  "address": {
    "street": "Fuhab Avenue",
    "city": "Adbemal",
    "state": "IA",
    "zip": "15880"
  },
  "contact": {
    "phone": "(454) 723-1360",
    "servicePhone": "800988815"
  },
  "birthday": "2004-05-15T10:06:17.464Z",
  "ip": "131.204.36.73",
  "foo": "bar",
  "profile": {
    "about": "Fag fe kitulag josogehe cetkegga gekfovis ceteb pab wunkud wi mughuf sasibu sujnevaz giicuzub co. Zoozowuf saccizpag jihu bev cik zuj utduhef nu ku vubecra ul bos emubesom tohsiwu ene ade. Ginmu cod va ovu kojlar legifuam begjus igivafbib tuti ciurze is dol boke kilsu geosouh. Vackunec hafat tubnocogi jok su di ale gebewso inu sal li fot afivo oz. Fuidi nof huahiveb vaekcu domuwof futfun maf pufuce hihwe cubbu keetuiso kizhodo gavaf sokajo isra.",
    "bio": "Getirpas lijla kaog cov cesjutsom tutivev apput wet jumgomi gu cijhuw kouveti ufinodoz rojazpe mefozde. Fa jija cas jisuvobi vu bimvi feje zunzu pitezeba ke fi pag mom juano jo tarajzor huj. Zo lapo cajud pagumbor opo cot olugudni daugiju rejsoc lize gawwofba fob paj jiziwmab nupkacbe pogbi hiwupu. Jofvin hepemu sajizeg wihtor bog dug her vi pewiec gavezela lucuplad hidat wilo wegmik zofuwi. Bamulak sudcovop azese azeubu encigip ohazup fodu bez raz ganuzwej ebriuhu buepuef."
  },
  "apiKey": "b80b6b9f54b9fdde52d02e92eb9f31c1608b547e431715cd303f5f2e805012ef",
  "currency": {
    "code": "XOF",
    "name": "Communauté Financière Africaine (BCEAO) Franc"
  }
}