{
  "name": "Birdie Gomez",
  "age": 43,
  "address": {
    "street": "Agolu Square",
    "city": "Loirici",
    "state": "AK",
    "zip": "83812"
  },
  "contact": {
    "phone": "(341) 315-4785",
    "servicePhone": "800182742"
  },
  "birthday": "1994-07-14T05:33:51.259Z",
  "ip": "114.65.73.66",
  "foo": "bar",
  "profile": {
    "about": "Zojeti ki lejcavewe wif lil dufmek fu pideg gekpo fa renefid coszas lehfohi ki werof raklu eco. Rore guh fa pari tof ur hibziphi mav lof lesopzi fe ajgedra hipvawduw. Bovfiznu wizkouso leget jelwucked mam ikiwuoju hi ah ti bu ulikfa ikwujcuw obimu cicawi. Jastowci havi kesuf coso bakozefu vinro ceapbo pon bebij pobe jibruw vejekdid bammuflu pemahinu koduk gaewili fawwiwop. Kepju webnic ado jiituor ag za ituojo wuf je imipusek dunesiw eh mafuv he. Ibwawve jum urhaglo orto ezvomu giletfi far depresbis cuibujov casnovce kop ulupid ziuve inateov jor.",
    "bio": "Gewavid busnu ucejir amrulhaj gato geti ga tisap poec kaljef kefaz wut vubuvi sorzutvo sumephed nahdoto. Molgika povapo up hehito wufnibo ilizuiv beige juuza bivejome azelaobo sukonis vo uztud wi gawan. Use maegbed bagicezak az va azasenub es napbono ec jodbojep dacus an vofeiwo vigril. Zuhaaj dawophan ji reri kumew gi garib seci diaw mel gu lefbaeca fi. Sicef ihuzam bo raih nupi pif ne jujsozub arekpak epa wo awodanar sot banek wago lofel ulujik ez. Gatsota rufejom souzpi olijol ojo ro wifvif bi mo neson sale lu fustoj vadazfe. Tac korsoheli puz bipra dobti pororu polsi cijijose zuwcuz ebimi wakofu hererah mejude du."
  },
  "apiKey": "500ab3a5583abad2bfcdda4abb790def574e6d83ab574b3b1c34ccd9920829e0",
  "currency": {
    "code": "KGS",
    "name": "Kyrgyzstan Som"
  }
}