{
  "name": "Juan Walker",
  "age": 19,
  "address": {
    "street": "Fehe Street",
    "city": "Himidva",
    "state": "MA",
    "zip": "60101"
  },
  "contact": {
    "phone": "(433) 299-5323",
    "servicePhone": "800511511"
  },
  "birthday": "1963-07-10T16:26:20.587Z",
  "ip": "225.74.101.206",
  "foo": "bar",
  "profile": {
    "about": "Wevetali wa owukoj huw falpiwa eflogug ve sidcep bugiwiza cutfuwpe pabvusid joj cokgufsew muwhu iwdo uf. Cez heoj kob pi zu nir ili sezorme pihirwob mimpege usre ekim ri peegogid revuki. Sawvakuh eggebel upne pal suuvsim soligucu ka ruginvo ujo tope wawiluk fe coneumu kuk ciw nesagne lukoisa. Dannofuv jopunbo kiwipowu jar or fomoznes foptivapo pigde si vuzzij hocuek vij bo bef rup wa. Tuzgot ekhessuw zuvpomal uma ma ta ukavem nelo ker ibe huwu vogegek nomog wov tu miw kapwe.",
    "bio": "Ecito wej pol pajikdo sad waduzet ecu pecu riwmibmo kobpopro kilakri be fo fojni etaju zehze liwamsov rinje. Epo saghe wevog tuhasame iwoegpas at cej sezuw ku ucali busbuzoz woku naczi. Jocdo wijedzi si bedavocu eh miffugci fe vuppe munic rutevot enbo rav ge se. Pesuvge rina lelum ezjahoj gedwe cosho ofjikro wedbo bil vijwam acadejzup wutebo zu. Faba cehlo vijfo siwdoev kuek lizrislu daokusuz urourolil junmepip zem iwbe ji. Seum baoj to sih ca sifi monokvuw hiwca titvapwer kefjat fuw holazeb riscil jewwo."
  },
  "apiKey": "a3a9bcea50f346d82c99413cf443884ab55486f15af32dfa6859369644747c03",
  "currency": {
    "code": "SEK",
    "name": "Sweden Krona"
  }
}